dumb_pypi/__init__.py
dumb_pypi/main.py
dumb_pypi/templates/_base.html
dumb_pypi/templates/changelog.html
dumb_pypi/templates/index.html
dumb_pypi/templates/package.html
dumb_pypi/templates/simple.html
dumb_pypi-1.15.0.dist-info/LICENSE
dumb_pypi-1.15.0.dist-info/METADATA
dumb_pypi-1.15.0.dist-info/WHEEL
dumb_pypi-1.15.0.dist-info/entry_points.txt
dumb_pypi-1.15.0.dist-info/top_level.txt
dumb_pypi-1.15.0.dist-info/RECORD
